LICENSE.txt
README.md
pyproject.toml
setup.cfg
src/load_shedding/__init__.py
src/load_shedding/load_shedding.py
src/load_shedding.egg-info/PKG-INFO
src/load_shedding.egg-info/SOURCES.txt
src/load_shedding.egg-info/dependency_links.txt
src/load_shedding.egg-info/requires.txt
src/load_shedding.egg-info/top_level.txt
src/load_shedding/libs/__init__.py
src/load_shedding/libs/citypower.py
src/load_shedding/libs/coct.py
src/load_shedding/libs/eskom.py
src/load_shedding/libs/sepush.py
src/load_shedding/providers/__init__.py
src/load_shedding/providers/citypower.py
src/load_shedding/providers/coct.py
src/load_shedding/providers/eskom.py
src/load_shedding/providers/sepush.py