Metadata-Version: 2.4
Name: load-shedding
Version: 0.12.2
Summary: A python library for getting Load Shedding schedules from Eskom.
Home-page: https://gitlab.com/wernerhp/load-shedding
Author: Werner Pieterson
Author-email: wernerhp@gmail.com
Project-URL: Bug Tracker, https://gitlab.com/wernerhp/load-shedding/issues
Keywords: eskom,load shedding,south africa,api
Classifier: Development Status :: 3 - Alpha
Classifier: Intended Audience :: Developers
Classifier: Topic :: Software Development :: Build Tools
Classifier: License :: OSI Approved :: GNU General Public License v3 or later (GPLv3+)
Classifier: Programming Language :: Python :: 3.9
Requires-Python: >=3.9
License-File: LICENSE.txt
Requires-Dist: beautifulsoup4~=4.9.3
Requires-Dist: certifi~=2021.10.8
Requires-Dist: urllib3[secure]>=1.26.7
Dynamic: license-file
